seakylib/__init__.py
seakylib/data/__init__.py
seakylib/data/mysql.py
seakylib/data/pd.py
seakylib/data/redis_func.py
seakylib/func/__init__.py
seakylib/func/base.py
seakylib/func/interactive.py
seakylib/func/log.py
seakylib/func/misc.py
seakylib/func/mrun.py
seakylib/func/parser.py
seakylib/func/string.py
seakylib/func/time.py
seakylib/net/__init__.py
seakylib/net/connectivity.py
seakylib/net/http.py
seakylib/net/ip.py
seakylib/net/proxy.py
seakylib/net/sserver.py
seakylib/notify/__init__.py
seakylib/notify/im.py
seakylib/notify/sendmail.py
seakylib/os/__init__.py
seakylib/os/cmd.py
seakylib/os/compress.py
seakylib/os/info.py
seakylib/os/oper.py
seakylib-1.0.6.5.dist-info/LICENSE
seakylib-1.0.6.5.dist-info/METADATA
seakylib-1.0.6.5.dist-info/WHEEL
seakylib-1.0.6.5.dist-info/top_level.txt
seakylib-1.0.6.5.dist-info/RECORD
