Metadata-Version: 2.1
Name: seakylib
Version: 1.0.6.5
Summary: Seaky's private lib
Home-page: https://github.com/sseaky
Author: Seaky
Author-email: seaky.cn@gmail.com
Classifier: Programming Language :: Python :: 3
Classifier: License :: OSI Approved :: MIT License
Classifier: Operating System :: OS Independent
License-File: LICENSE
Requires-Dist: beautifulsoup4
Requires-Dist: IPy
Requires-Dist: numpy
Requires-Dist: pandas
Requires-Dist: psutil
Requires-Dist: puresnmp
Requires-Dist: PyMySQL
Requires-Dist: requests
Requires-Dist: SocksiPy-branch
Requires-Dist: sqlacodegen
Requires-Dist: SQLAlchemy
Requires-Dist: sshtunnel
Requires-Dist: urllib3
Requires-Dist: concurrent-log-handler
Requires-Dist: xlrd
Requires-Dist: openpyxl
Requires-Dist: redis
